babbagecoin/__init__.py
babbagecoin/__main__.py
babbagecoin/client/__init__.py
babbagecoin/client/__main__.py
babbagecoin/client/client.py
babbagecoin/common/__init__.py
babbagecoin/common/balance.py
babbagecoin/common/block_service.py
babbagecoin/common/context.py
babbagecoin/common/exceptions.py
babbagecoin/common/models.py
babbagecoin/common/schemas.py
babbagecoin/common/wallet.py
babbagecoin/master/__init__.py
babbagecoin/master/blockchain_service.py
babbagecoin/master/broadcast_service.py
babbagecoin/master/routes.py
babbagecoin/master/transaction_service.py
babbagecoin/miner/__init__.py
babbagecoin/miner/miner.py
babbagecoin/webclient/assets/index.0a45b0c5.css
babbagecoin/webclient/assets/index.7a2daf10.js
babbagecoin/webclient/index.html
babbagecoin/webclient/vite.svg
babbagecoin-0.5.0.dist-info/WHEEL
babbagecoin-0.5.0.dist-info/METADATA
babbagecoin-0.5.0.dist-info/RECORD
